pydnserver/__init__.py
pydnserver/_constants.py
pydnserver/_exceptions.py
pydnserver/_metadata.py
pydnserver/dns_query.py
pydnserver/dns_server.py
pydnserver/config/__init__.py
pydnserver/config/dns_forwarders.py
pydnserver/config/dns_lookup.py
pydnserver/gui/__init__.py
pydnserver/gui/frame/__init__.py
pydnserver/gui/frame/dns_config.py
pydnserver/gui/frame/forwarder.py
pydnserver/gui/frame/forwarders.py
pydnserver/gui/frame/record.py
pydnserver/gui/frame/server.py
pydnserver/gui/frame/zone.py
pydnserver/gui/window/__init__.py
pydnserver/gui/window/dns_config.py
pydnserver/gui/window/forwarder.py
pydnserver/gui/window/forwarders.py
pydnserver/gui/window/record.py
pydnserver/gui/window/server.py
pydnserver/gui/window/zone.py
pydnserver/resources/__init__.py
pydnserver/resources/schema/__init__.py
pydnserver/resources/schema/dns_forwarders.json
pydnserver/resources/schema/dns_lookup.json
pydnserver/resources/templates/__init__.py
pydnserver/resources/templates/dns_forwarders.json
pydnserver/resources/templates/dns_lookup.json
pydnserver/unittests/__init__.py
pydnserver/unittests/dns_query.py
pydnserver/unittests/test_dns_forwarders.py
pydnserver/unittests/test_dns_lookup.py
pydnserver-2.4.2.dist-info/LICENSE.txt
pydnserver-2.4.2.dist-info/METADATA
pydnserver-2.4.2.dist-info/WHEEL
pydnserver-2.4.2.dist-info/entry_points.txt
pydnserver-2.4.2.dist-info/top_level.txt
pydnserver-2.4.2.dist-info/RECORD
