Metadata-Version: 2.1
Name: pydnserver
Version: 2.4.2
Summary: Provides a very simple DNS server.
Home-page: https://bitbucket.org/davisowb/pydnserver.git
Author: Oli Davis & Hywel Thomas
Author-email: oli.davis@me.com, hywel.thomas@mac.com
License: MIT
Download-URL: https://bitbucket.org/davisowb/pydnserver.git/get/2.4.2.tar
Keywords: dns
Platform: UNKNOWN
Classifier: Development Status :: 3 - Alpha
Classifier: Intended Audience :: Developers
Classifier: License :: OSI Approved :: MIT License
Classifier: Programming Language :: Python :: 2
Classifier: Programming Language :: Python :: 2.7
Classifier: Programming Language :: Python :: 3
Classifier: Programming Language :: Python :: 3.6
Classifier: Topic :: Utilities
License-File: LICENSE.txt
Requires-Dist: pip (>=18.1)
Requires-Dist: future (>=0.16.0)
Requires-Dist: dnspython (==1.16.0)
Requires-Dist: logging-helper (>=1.8.4)
Requires-Dist: configurationutil[ui] (>=3.7.5)
Requires-Dist: tableutil (>=2.4.0)
Requires-Dist: uiutil (>=1.33.0)
Requires-Dist: networkutil (>=1.19.4)
Requires-Dist: fdutil (>=1.8.1)
Requires-Dist: classutils (>=1.11.3)
Requires-Dist: ipaddress (>=1.0.19)
Requires-Dist: apiutil (>=1.9.4)
